AESencrypter/__init__.py
AESencrypt-0.0.5.dist-info/LICENSE
AESencrypt-0.0.5.dist-info/METADATA
AESencrypt-0.0.5.dist-info/WHEEL
AESencrypt-0.0.5.dist-info/top_level.txt
AESencrypt-0.0.5.dist-info/RECORD
