Metadata-Version: 2.1
Name: AESencrypt
Version: 0.0.5
Summary: tool for encrypting files using AES encryption
Home-page: https://github.com/AhmadTaj1754/AESencrypter
Author: Ahmad Taj
Author-email: Ahmadtaj77@gmail.com
License: UNKNOWN
Platform: UNKNOWN
Classifier: Programming Language :: Python :: 2
Classifier: License :: OSI Approved :: MIT License
Classifier: Operating System :: OS Independent
